{
    "name": "Global Information",
    "numberOfRequests": {
        "total": 46500,
        "ok": 46500,
        "ko": 0
    },
    "minResponseTime": {
        "total": 11,
        "ok": 11,
        "ko": 0
    },
    "maxResponseTime": {
        "total": 1745,
        "ok": 1745,
        "ko": 0
    },
    "meanResponseTime": {
        "total": 291,
        "ok": 291,
        "ko": 0
    },
    "standardDeviation": {
        "total": 237,
        "ok": 237,
        "ko": 0
    },
    "percentiles1": {
        "total": 249,
        "ok": 249,
        "ko": 0
    },
    "percentiles2": {
        "total": 449,
        "ok": 449,
        "ko": 0
    },
    "percentiles3": {
        "total": 715,
        "ok": 715,
        "ko": 0
    },
    "percentiles4": {
        "total": 905,
        "ok": 905,
        "ko": 0
    },
    "group1": {
        "name": "t < 800 ms",
        "count": 45428,
        "percentage": 98
    },
    "group2": {
        "name": "800 ms < t < 1200 ms",
        "count": 924,
        "percentage": 2
    },
    "group3": {
        "name": "t > 1200 ms",
        "count": 148,
        "percentage": 0
    },
    "group4": {
        "name": "failed",
        "count": 0,
        "percentage": 0
    },
    "meanNumberOfRequestsPerSecond": {
        "total": 312.08053691275165,
        "ok": 312.08053691275165,
        "ko": 0
    }
}