{
    "name": "Global Information",
    "numberOfRequests": {
        "total": 46500,
        "ok": 46500,
        "ko": 0
    },
    "minResponseTime": {
        "total": 10,
        "ok": 10,
        "ko": 0
    },
    "maxResponseTime": {
        "total": 1221,
        "ok": 1221,
        "ko": 0
    },
    "meanResponseTime": {
        "total": 124,
        "ok": 124,
        "ko": 0
    },
    "standardDeviation": {
        "total": 108,
        "ok": 108,
        "ko": 0
    },
    "percentiles1": {
        "total": 90,
        "ok": 90,
        "ko": 0
    },
    "percentiles2": {
        "total": 183,
        "ok": 183,
        "ko": 0
    },
    "percentiles3": {
        "total": 335,
        "ok": 335,
        "ko": 0
    },
    "percentiles4": {
        "total": 452,
        "ok": 452,
        "ko": 0
    },
    "group1": {
        "name": "t < 800 ms",
        "count": 46482,
        "percentage": 100
    },
    "group2": {
        "name": "800 ms < t < 1200 ms",
        "count": 17,
        "percentage": 0
    },
    "group3": {
        "name": "t > 1200 ms",
        "count": 1,
        "percentage": 0
    },
    "group4": {
        "name": "failed",
        "count": 0,
        "percentage": 0
    },
    "meanNumberOfRequestsPerSecond": {
        "total": 325.1748251748252,
        "ok": 325.1748251748252,
        "ko": 0
    }
}