{
    "name": "Global Information",
    "numberOfRequests": {
        "total": 52500,
        "ok": 52500,
        "ko": 0
    },
    "minResponseTime": {
        "total": 10,
        "ok": 10,
        "ko": 0
    },
    "maxResponseTime": {
        "total": 4430,
        "ok": 4430,
        "ko": 0
    },
    "meanResponseTime": {
        "total": 186,
        "ok": 186,
        "ko": 0
    },
    "standardDeviation": {
        "total": 338,
        "ok": 338,
        "ko": 0
    },
    "percentiles1": {
        "total": 44,
        "ok": 44,
        "ko": 0
    },
    "percentiles2": {
        "total": 187,
        "ok": 187,
        "ko": 0
    },
    "percentiles3": {
        "total": 847,
        "ok": 847,
        "ko": 0
    },
    "percentiles4": {
        "total": 1630,
        "ok": 1631,
        "ko": 0
    },
    "group1": {
        "name": "t < 800 ms",
        "count": 49600,
        "percentage": 94
    },
    "group2": {
        "name": "800 ms < t < 1200 ms",
        "count": 1668,
        "percentage": 3
    },
    "group3": {
        "name": "t > 1200 ms",
        "count": 1232,
        "percentage": 2
    },
    "group4": {
        "name": "failed",
        "count": 0,
        "percentage": 0
    },
    "meanNumberOfRequestsPerSecond": {
        "total": 357.14285714285717,
        "ok": 357.14285714285717,
        "ko": 0
    }
}