{
    "name": "Global Information",
    "numberOfRequests": {
        "total": 46500,
        "ok": 46500,
        "ko": 0
    },
    "minResponseTime": {
        "total": 11,
        "ok": 11,
        "ko": 0
    },
    "maxResponseTime": {
        "total": 2059,
        "ok": 2059,
        "ko": 0
    },
    "meanResponseTime": {
        "total": 307,
        "ok": 307,
        "ko": 0
    },
    "standardDeviation": {
        "total": 284,
        "ok": 284,
        "ko": 0
    },
    "percentiles1": {
        "total": 232,
        "ok": 232,
        "ko": 0
    },
    "percentiles2": {
        "total": 439,
        "ok": 439,
        "ko": 0
    },
    "percentiles3": {
        "total": 875,
        "ok": 875,
        "ko": 0
    },
    "percentiles4": {
        "total": 1133,
        "ok": 1132,
        "ko": 0
    },
    "group1": {
        "name": "t < 800 ms",
        "count": 42894,
        "percentage": 92
    },
    "group2": {
        "name": "800 ms < t < 1200 ms",
        "count": 3286,
        "percentage": 7
    },
    "group3": {
        "name": "t > 1200 ms",
        "count": 320,
        "percentage": 1
    },
    "group4": {
        "name": "failed",
        "count": 0,
        "percentage": 0
    },
    "meanNumberOfRequestsPerSecond": {
        "total": 314.18918918918916,
        "ok": 314.18918918918916,
        "ko": 0
    }
}